setup.py
cognizance/__init__.py
cognizance/admin.py
cognizance/models.py
cognizance/urls.py
cognizance/migrations/0001_initial.py
cognizance/migrations/0002_initial.py
cognizance/migrations/0003_auto__chg_field_entry_views__chg_field_entry_excerpt__chg_field_entry_.py
cognizance/migrations/__init__.py
django-cognizance.egg-info/PKG-INFO
django-cognizance.egg-info/SOURCES.txt
django-cognizance.egg-info/dependency_links.txt
django-cognizance.egg-info/not-zip-safe
django-cognizance.egg-info/requires.txt
django-cognizance.egg-info/top_level.txt